<?xml version='1.0' encoding='utf-8'?>
<odoo>
    <!-- homade.karbohidrat tree view -->
    <record id="homade_karbo_view_tree" model="ir.ui.view">
        <field name="name">Jenis Karbohidrat</field>
        <field name="model">homade.karbohidrat</field>
        <field name="arch" type="xml">
            <tree>
                <field name="name"/>
                <field name="deskripsi"/>
                <field name="harga"/>
            </tree>
        </field>
    </record>

    <!-- homade.karbohidrat form view -->
    <record id="homade_karbo_view_form" model="ir.ui.view">
        <field name="name">Karbohidrat</field>
        <field name="model">homade.karbohidrat</field>
        <field name="arch" type="xml">
            <form string="">
                <sheet>
                    <group>
                        <field name="name"/>
                        <field name="deskripsi"/>
                        <field name="harga"/>
                    </group>
                </sheet>
            </form>
        </field>
    </record>

    <!-- homade.karbohidrat action window -->
    <record id="homade_karbo_action" model="ir.actions.act_window">
        <field name="name">Daftar Karbohidrat</field>
        <field name="type">ir.actions.act_window</field>
        <field name="res_model">homade.karbohidrat</field>
        <field name="view_mode">tree,form</field>
    </record>

    <!-- This Menu Item must have a parent and an action -->
    <menuitem 
    id="homade_karbo_menu_act"
    name="Karbohidrat" 
    parent="homade_daftarmakanan_menu_categ" 
    action="homade_karbo_action" 
    sequence="20"/>
</odoo>